dizzy.py
bsit_dizzy-0.1.0.dist-info/licenses/LICENSE
bsit_dizzy-0.1.0.dist-info/METADATA
bsit_dizzy-0.1.0.dist-info/WHEEL
bsit_dizzy-0.1.0.dist-info/top_level.txt
bsit_dizzy-0.1.0.dist-info/RECORD
