Metadata-Version: 2.4
Name: bsit-dizzy
Version: 0.1.0
Summary: Add your description here
Requires-Python: >=3.13
License-File: LICENSE
Requires-Dist: rdflib>=7.1.4
Dynamic: license-file
